MANIFEST.in
NEWS.txt
README.rst
setup.py
multiwait/__init__.py
multiwait/cli.py
multiwait/exceptions.py
multiwait/utils.py
multiwait.egg-info/PKG-INFO
multiwait.egg-info/SOURCES.txt
multiwait.egg-info/dependency_links.txt
multiwait.egg-info/entry_points.txt
multiwait.egg-info/not-zip-safe
multiwait.egg-info/requires.txt
multiwait.egg-info/top_level.txt
multiwait/modules/__init__.py
multiwait/modules/base.py
multiwait/modules/files.py
multiwait/modules/redis.py
multiwait/modules/x11.py
multiwait/tests/__init__.py
multiwait/tests/test_modules.py