Metadata-Version: 1.0
Name: multiwait
Version: 0.2.1
Summary: Wait for stuff to happen before running a command
Home-page: https://github.com/flupke/multiwait
Author: Luper Rouch
Author-email: luper.rouch@gmail.com
License: MIT
Platform: UNKNOWN
